data_minimization_tools/__init__.py
data_minimization_tools/bla.txt
data_minimization_tools/cvdi/__init__.py
data_minimization_tools/cvdi/bin/Dockerfile
data_minimization_tools/cvdi/bin/LICENSE
data_minimization_tools/cvdi/bin/cv_di
data_minimization_tools/cvdi/bin/cv_di.exe
data_minimization_tools/utils/__init__.py
data_minimization_tools/utils/generate_config.py
data_minimization_tools/utils/kanon_cn_config.py
data_minimization_tools-0.1.3.dist-info/LICENSE
data_minimization_tools-0.1.3.dist-info/METADATA
data_minimization_tools-0.1.3.dist-info/WHEEL
data_minimization_tools-0.1.3.dist-info/top_level.txt
data_minimization_tools-0.1.3.dist-info/RECORD
