Metadata-Version: 2.1
Name: data-minimization-tools
Version: 0.1.3
Summary: Pyhton library for data minimization tools.
Home-page: https://github.com/peng-data-minimization/minimizer
Author: peng-data-minimization
Author-email: peng.dataminimization@gmail.com
License: MIT
Platform: UNKNOWN
Requires-Dist: numpy
Requires-Dist: PyYAML
Requires-Dist: pandas
